payload_automation/__init__.py
payload_automation/artifactor.py
payload_automation/beacon.py
payload_automation/compyler.py
payload_automation/detemplate.py
payload_automation/sleepy.py
payload_automation/striker.py
payload_automation-1.1.0.dist-info/LICENSE.txt
payload_automation-1.1.0.dist-info/METADATA
payload_automation-1.1.0.dist-info/WHEEL
payload_automation-1.1.0.dist-info/top_level.txt
payload_automation-1.1.0.dist-info/RECORD
