Metadata-Version: 2.1
Name: payload-automation
Version: 1.1.0
Summary: A set of libraries to help be a bridge between Sleep and Python, helping to automate payload development, testing, opsec checking, beacon tasking, and deployment for Cobalt Strike
Home-page: https://github.com/emcghee/PayloadAutomation
Author: Faultline
Author-email: jahawkins623@gmail.com
License: UNKNOWN
Download-URL: https://github.com/emcghee/PayloadAutomation/archive/refs/tags/1.0.1.tar.gz
Platform: UNKNOWN
Classifier: Programming Language :: Python :: 3
Classifier: License :: OSI Approved :: GNU General Public License v3 (GPLv3)
Classifier: Operating System :: OS Independent
Requires-Python: >=3.6
Requires-Dist: javaobj-py3 (>=0.4.1)
Requires-Dist: pepy (>=1.2.0)
Requires-Dist: ptyprocess (>=0.5)
Requires-Dist: pexpect
Requires-Dist: magicfile
Requires-Dist: PyYAML (==5.4.1)
